touchtechnology/__init__.py
touchtechnology/admin/__init__.py
touchtechnology/admin/apps.py
touchtechnology/admin/base.py
touchtechnology/admin/forms.py
touchtechnology/admin/mixins.py
touchtechnology/admin/models.py
touchtechnology/admin/locale/de/LC_MESSAGES/django.mo
touchtechnology/admin/locale/de/LC_MESSAGES/django.po
touchtechnology/admin/locale/en-AU/LC_MESSAGES/django.mo
touchtechnology/admin/locale/en-AU/LC_MESSAGES/django.po
touchtechnology/admin/locale/fr/LC_MESSAGES/django.mo
touchtechnology/admin/locale/fr/LC_MESSAGES/django.po
touchtechnology/admin/locale/ja/LC_MESSAGES/django.mo
touchtechnology/admin/locale/ja/LC_MESSAGES/django.po
touchtechnology/admin/sites/__init__.py
touchtechnology/admin/sites/admin.py
touchtechnology/admin/sites/auth.py
touchtechnology/admin/sites/settings.py
touchtechnology/admin/static/bootstrap/CHANGELOG.md
touchtechnology/admin/static/bootstrap/Gruntfile.js
touchtechnology/admin/static/bootstrap/bower.json
touchtechnology/admin/static/bootstrap/package.js
touchtechnology/admin/static/bootstrap/package.json
touchtechnology/admin/static/bootstrap/dist/css/bootstrap-theme.css
touchtechnology/admin/static/bootstrap/dist/css/bootstrap-theme.css.map
touchtechnology/admin/static/bootstrap/dist/css/bootstrap-theme.min.css
touchtechnology/admin/static/bootstrap/dist/css/bootstrap-theme.min.css.map
touchtechnology/admin/static/bootstrap/dist/css/bootstrap.css
touchtechnology/admin/static/bootstrap/dist/css/bootstrap.css.map
touchtechnology/admin/static/bootstrap/dist/css/bootstrap.min.css
touchtechnology/admin/static/bootstrap/dist/css/bootstrap.min.css.map
touchtechnology/admin/static/bootstrap/dist/fonts/glyphicons-halflings-regular.eot
touchtechnology/admin/static/bootstrap/dist/fonts/glyphicons-halflings-regular.svg
touchtechnology/admin/static/bootstrap/dist/fonts/glyphicons-halflings-regular.ttf
touchtechnology/admin/static/bootstrap/dist/fonts/glyphicons-halflings-regular.woff
vitriolic-4.8.0.dist-info/licenses/LICENSE
vitriolic-4.8.0.dist-info/METADATA
vitriolic-4.8.0.dist-info/WHEEL
vitriolic-4.8.0.dist-info/top_level.txt
vitriolic-4.8.0.dist-info/RECORD
