Metadata-Version: 2.4
Name: vitriolic
Version: 4.8.0
Summary: A suite of packages for the Django framework to provide integrated Content Management and Sports Administration functionality for sporting associations.
Author-email: Gary Reynolds <gary@touch.asn.au>
License-Expression: BSD-3-Clause
Project-URL: Source Code, https://github.com/goodtune/vitriolic
Requires-Python: <3.15,>=3.11
License-File: LICENSE
Requires-Dist: django-froala-editor>=2.9
Requires-Dist: django-guardian>=2.4
Requires-Dist: django-mcp-server>=0.5.5
Requires-Dist: django-modelforms
Requires-Dist: django-mptt
Requires-Dist: django-timezone-field
Requires-Dist: django>=4.2
Requires-Dist: first
Requires-Dist: namedentities
Requires-Dist: psycopg
Provides-Extra: admin
Requires-Dist: django-bootstrap3; extra == "admin"
Requires-Dist: django-gravatar2; extra == "admin"
Provides-Extra: common
Provides-Extra: content
Provides-Extra: news
Requires-Dist: babel; extra == "news"
Requires-Dist: django-imagekit; extra == "news"
Requires-Dist: python-dateutil; extra == "news"
Requires-Dist: python-magic; extra == "news"
Provides-Extra: competition
Requires-Dist: pydantic>=2.0; extra == "competition"
Requires-Dist: celery>5; extra == "competition"
Requires-Dist: cloudinary; extra == "competition"
Requires-Dist: django-embed-video; extra == "competition"
Requires-Dist: django-filter; extra == "competition"
Requires-Dist: django-formtools; extra == "competition"
Requires-Dist: django-htmx>=1.23.2; extra == "competition"
Requires-Dist: django-mathfilters; extra == "competition"
Requires-Dist: djangorestframework>3.11; extra == "competition"
Requires-Dist: drf-nested-routers; extra == "competition"
Requires-Dist: google-api-python-client; extra == "competition"
Requires-Dist: google-auth-oauthlib; extra == "competition"
Requires-Dist: icalendar; extra == "competition"
Requires-Dist: internationaltouch-oauth2client; extra == "competition"
Requires-Dist: markdown; extra == "competition"
Requires-Dist: pyparsing; extra == "competition"
Requires-Dist: python-dateutil; extra == "competition"
Requires-Dist: python-magic; extra == "competition"
Provides-Extra: redis
Dynamic: license-file
